noahs_openai_agent/__init__.py
noahs_openai_agent/agent.py
noahs_openai_agent/agent_tools.py
noahs_openai_agent/basic_web_scraping.py
noahs_openai_agent/local_semantic_db.py
noahs_openai_agent/local_sql_db.py
noahs_openai_agent/semantic_text_splitter.py
noahs_openai_agent-0.1.2.dist-info/METADATA
noahs_openai_agent-0.1.2.dist-info/WHEEL
noahs_openai_agent-0.1.2.dist-info/top_level.txt
noahs_openai_agent-0.1.2.dist-info/RECORD
