Metadata-Version: 2.4
Name: noahs_openai_agent
Version: 0.1.2
Summary: A openai api agent module with semantic DB, SQL, and web scraping tools.
Author-email: Noah Jones <jonesnoah45010@gmail.com>
License: MIT
Project-URL: Homepage, https://github.com/jonesnoah45010/openai_agent
Requires-Python: >=3.9
Requires-Dist: chromadb
Requires-Dist: transformers
Requires-Dist: torch==2.1.0
Requires-Dist: sentence-transformers
Requires-Dist: numpy<2.0
Requires-Dist: textsplit
Requires-Dist: beautifulsoup4
Requires-Dist: requests
Requires-Dist: openai
Requires-Dist: tiktoken
Requires-Dist: asyncio
